pkybrowser/DB.py
pkybrowser/__init__.py
pkybrowser/baseChrome.py
pkybrowser/baseFirefox.py
pkybrowser/basicBrowser.py
pkybrowser/myBrowser.py
pkybrowser/myBrowser2.py
pkybrowser/utils.py
pkybrowser/LIB/__init__.py
pkybrowser/LIB/logger.py
pkybrowser/LIB/yaml_read.py
pkybrowser-0.0.1.dist-info/METADATA
pkybrowser-0.0.1.dist-info/WHEEL
pkybrowser-0.0.1.dist-info/top_level.txt
pkybrowser-0.0.1.dist-info/RECORD
